mental_models/__init__.py
mental_models/auto_map.py
mental_models/similarity.py
mental_models/utils/__init__.py
mental_models-0.1.5.dist-info/LICENSE
mental_models-0.1.5.dist-info/METADATA
mental_models-0.1.5.dist-info/WHEEL
mental_models-0.1.5.dist-info/top_level.txt
mental_models-0.1.5.dist-info/RECORD
